pydvl/__init__.py
pydvl/py.typed
pydvl/influence/__init__.py
pydvl/influence/array.py
pydvl/influence/base_influence_function_model.py
pydvl/influence/influence_calculator.py
pydvl/influence/types.py
pydvl/influence/torch/__init__.py
pydvl/influence/torch/base.py
pydvl/influence/torch/batch_operation.py
pydvl/influence/torch/functional.py
pydvl/influence/torch/influence_function_model.py
pydvl/influence/torch/operator.py
pydvl/influence/torch/preconditioner.py
pydvl/influence/torch/util.py
pydvl/parallel/__init__.py
pydvl/parallel/backend.py
pydvl/parallel/config.py
pydvl/parallel/map_reduce.py
pydvl/parallel/backends/__init__.py
pydvl/parallel/backends/joblib.py
pydvl/parallel/backends/ray.py
pydvl/parallel/futures/__init__.py
pydvl/parallel/futures/ray.py
pydvl/reporting/__init__.py
pydvl/reporting/plots.py
pydvl/reporting/point_removal.py
pydvl/reporting/scores.py
pydvl/utils/__init__.py
pydvl/utils/dataset.py
pydvl/utils/exceptions.py
pydvl/utils/functional.py
pydvl/utils/monitor.py
pydvl/utils/numeric.py
pydvl/utils/progress.py
pydvl/utils/score.py
pydvl/utils/status.py
pydvl/utils/types.py
pydvl/utils/utility.py
pydvl/utils/caching/__init__.py
pydvl/utils/caching/base.py
pydvl/utils/caching/config.py
pydvl/utils/caching/disk.py
pydvl/utils/caching/memcached.py
pydvl/utils/caching/memory.py
pydvl/valuation/__init__.py
pydvl/valuation/base.py
pydvl/valuation/dataset.py
pydvl/valuation/games.py
pydvl/valuation/parallel.py
pydvl/valuation/result.py
pydvl/valuation/stopping.py
pydvl/valuation/types.py
pydvl/valuation/methods/__init__.py
pydvl/valuation/methods/_solve_least_core_problems.py
pydvl/valuation/methods/_utility_values_and_sample_masks.py
pydvl/valuation/methods/banzhaf.py
pydvl/valuation/methods/beta_shapley.py
pydvl/valuation/methods/classwise_shapley.py
pydvl/valuation/methods/data_oob.py
pydvl/valuation/methods/delta_shapley.py
pydvl/valuation/methods/gt_shapley.py
pydvl/valuation/methods/knn_shapley.py
pydvl/valuation/methods/least_core.py
pyDVL-0.10.0.dist-info/COPYING.LESSER
pyDVL-0.10.0.dist-info/LICENSE
pyDVL-0.10.0.dist-info/METADATA
pyDVL-0.10.0.dist-info/WHEEL
pyDVL-0.10.0.dist-info/top_level.txt
pyDVL-0.10.0.dist-info/RECORD
