Metadata-Version: 2.1
Name: pyDVL
Version: 0.10.0
Summary: The Python Data Valuation Library
Author: appliedAI Institute gGmbH
Project-URL: Source, https://github.com/aai-institute/pydvl
Project-URL: Documentation, https://pydvl.org
Project-URL: TransferLab, https://transferlab.ai
Classifier: Development Status :: 4 - Beta
Classifier: Intended Audience :: Science/Research
Classifier: Topic :: Scientific/Engineering :: Artificial Intelligence
Classifier: Programming Language :: Python :: 3.9
Classifier: Programming Language :: Python :: 3.10
Classifier: Programming Language :: Python :: 3.11
Classifier: Programming Language :: Python :: 3.12
Classifier: Typing :: Typed
Classifier: Operating System :: MacOS :: MacOS X
Classifier: Operating System :: Microsoft :: Windows
Classifier: Operating System :: POSIX
Classifier: License :: OSI Approved :: GNU Lesser General Public License v3 (LGPLv3)
License-File: LICENSE
License-File: COPYING.LESSER
Requires-Dist: pyDeprecate>=0.3.2
Requires-Dist: more-itertools>=9.0.0
Requires-Dist: numpy<2,>=1.20
Requires-Dist: pandas>=1.3
Requires-Dist: scikit-learn>=1.3
Requires-Dist: scipy>=1.7.0
Requires-Dist: cvxpy>=1.3.0
Requires-Dist: joblib>=1.4.0
Requires-Dist: cloudpickle
Requires-Dist: psutil
Requires-Dist: tqdm
Requires-Dist: matplotlib
Requires-Dist: typing-extensions
Requires-Dist: numcodecs<0.16.0
Provides-Extra: cupy
Requires-Dist: cupy-cuda11x>=12.1.0; extra == "cupy"
Provides-Extra: influence
Requires-Dist: torch>=2.0.0; extra == "influence"
Requires-Dist: dask>=2023.5.0; extra == "influence"
Requires-Dist: distributed>=2023.5.0; extra == "influence"
Requires-Dist: zarr<3,>=2; python_version < "3.11" and extra == "influence"
Requires-Dist: numcodecs<0.16.0; python_version < "3.11" and extra == "influence"
Requires-Dist: zarr<4,>=3; python_version >= "3.11" and extra == "influence"
Provides-Extra: memcached
Requires-Dist: pymemcache; extra == "memcached"
Provides-Extra: ray
Requires-Dist: ray>=0.8; extra == "ray"
